Metadata-Version: 2.1
Name: py-directus
Version: 0.0.30
Summary: Python wrapper for asynchronous interaction with Directus
Home-page: https://github.com/panos-stavrianos/py-directus
Author: Panos Stavrianos
Author-email: panos@orbitsystems.gr
License: MIT license
Keywords: python,directus,async,asyncio,api,wrapper
Requires-Python: >=3.6
License-File: LICENSE
Requires-Dist: aiofiles >=23.2.1
Requires-Dist: httpx <1.0.0,>=0.25.0
Requires-Dist: json-fix <1.0.0,>=0.5.2
Requires-Dist: python-dotenv <2.0.0,>=1.0.0
Requires-Dist: python-magic <1.0.0,>=0.4.27
Requires-Dist: pydantic >2.0
Requires-Dist: rich <14.0.0,>=13.6.0
Requires-Dist: websockets >=11.0.3
Requires-Dist: platformdirs
Provides-Extra: fastapi
Requires-Dist: anyio <4.0.0,>=3.7.1 ; extra == 'fastapi'
Requires-Dist: fastapi ; extra == 'fastapi'
Requires-Dist: starlette ; extra == 'fastapi'
